[
    {
      "id": 1,
      "title": "His mother had always taught him",
      "body": "His mother had always taught him not to ever think of himself as better than others. He'd tried to live by this motto. He never looked down on those who were less fortunate or who had less money than him. But the stupidity of the group of people he was talking to made him change his mind.",
      "tags": ["history", "american", "crime"],
      "reactions": {
        "likes": 192,
        "dislikes": 25,
        "comments" : 0
      },
      "views": 305,
      "userId": 121,
      "image": "https://images.unsplash.com/photo-1524504388940-b1c1722653e1?auto=format&fit=crop&w=800&q=80"
    },
    {
      "id": 2,
      "title": "Walking through forgotten streets",
      "body": "He wandered through narrow streets once full of laughter. Now only silence remained, echoing stories no one remembered anymore.",
      "tags": ["travel", "mystery", "urban"],
      "reactions": {
        "likes": 289,
        "dislikes": 13,
        "comments" : 1
      },
      "views": 520,
      "userId": 122
    },
    {
      "id": 3,
      "title": "The abandoned journal",
      "body": "In the attic, she found a journal with cracked leather. Dust covered its secrets, but every word inside pulsed with life.",
      "tags": ["fiction", "diary", "nostalgia"],
      "reactions": {
        "likes": 158,
        "dislikes": 9,
        "comments" : 3
      },
      "views": 401,
      "userId": 123,
      "image": "https://images.unsplash.com/photo-1519681393784-d120267933ba?auto=format&fit=crop&w=800&q=80"
    },
    {
      "id": 4,
      "title": "Cracks in the concrete",
      "body": "Even the strongest walls can crack under pressure. He learned this the hard way in both life and architecture.",
      "tags": ["life", "philosophy", "urban"],
      "reactions": {
        "likes": 342,
        "dislikes": 30,
        "comments" : 6
      },
      "views": 610,
      "userId": 124
    },
    {
      "id": 5,
      "title": "Shadows in the woods",
      "body": "The deeper she walked into the woods, the more the shadows felt alive. Watching. Whispering. Waiting.",
      "tags": ["thriller", "nature", "dark"],
      "reactions": {
        "likes": 267,
        "dislikes": 18,
        "comments" : 45
      },
      "views": 486,
      "userId": 125,
      "image": "https://images.unsplash.com/photo-1502082553048-f009c37129b9?auto=format&fit=crop&w=800&q=80"
    }
  ]